minidata/__init__.py
minidata/demo.py
minidata/clis/README.md
minidata/clis/__init__.py
minidata/clis/cli.py
minidata/data/README.md
minidata/data/情感分析/携程酒店评论.ft
minidata/data/文本匹配/ATEC.ft
minidata/data/文本匹配/BQ.ft
minidata/data/文本匹配/LCQMC.ft
minidata/data/文本匹配/PAWSX.ft
minidata/data/文本匹配/STS-B.ft
minidata/data/文本匹配/__init__.py
minidata/data/文本匹配/sts.ft
minidata/data/文本匹配/同花顺相似问.ft
minidata/data/文本匹配/微众银行智能客服相似问.ft
minidata/data/文本匹配/蚂蚁金服相似问.ft
minidata/data/词库/字段词根字典.ft
minidata/data/词库/敏感词.ft
minidata/model/ckiplab/albert-tiny-chinese/config.json
minidata/model/ckiplab/albert-tiny-chinese/pytorch_model.bin
minidata/model/ckiplab/albert-tiny-chinese/special_tokens_map.json
minidata/model/ckiplab/albert-tiny-chinese/tokenizer_config.json
minidata/model/ckiplab/albert-tiny-chinese/vocab.txt
minidata-2022.4.28.13.35.59.dist-info/AUTHORS.rst
minidata-2022.4.28.13.35.59.dist-info/LICENSE
minidata-2022.4.28.13.35.59.dist-info/METADATA
minidata-2022.4.28.13.35.59.dist-info/WHEEL
minidata-2022.4.28.13.35.59.dist-info/entry_points.txt
minidata-2022.4.28.13.35.59.dist-info/top_level.txt
minidata-2022.4.28.13.35.59.dist-info/RECORD
