Metadata-Version: 2.1
Name: minidata
Version: 2022.4.28.13.35.59
Summary: 小数据小模型
Home-page: https://github.com/Jie-Yuan/minidata
Author: minidata
Author-email: yuanjie@xiaomi.com
License: MIT license
Keywords: minidata
Platform: UNKNOWN
Classifier: Development Status :: 2 - Pre-Alpha
Classifier: Intended Audience :: Developers
Classifier: License :: OSI Approved :: MIT License
Classifier: Natural Language :: English
Classifier: Programming Language :: Python :: 3
Classifier: Programming Language :: Python :: 3.6
Classifier: Programming Language :: Python :: 3.7
Classifier: Programming Language :: Python :: 3.8
Requires-Python: >=3.6
License-File: LICENSE
License-File: AUTHORS.rst
Requires-Dist: meutils
